model2queue/__init__.py
model2queue/api_tasks.py
model2queue/examples/__init__.py
model2queue/examples/fastapi/__init__.py
model2queue/examples/fastapi/preprocess_images.py
model2queue/examples/fastapi/simple_model.py
model2queue/helper/__init__.py
model2queue/helper/logger.py
model2queue/workers/__init__.py
model2queue/workers/consumer.py
model2queue/workers/consumer_producer.py
model2queue/workers/worker_thread.py
model2queue-0.1.9.dist-info/METADATA
model2queue-0.1.9.dist-info/WHEEL
model2queue-0.1.9.dist-info/top_level.txt
model2queue-0.1.9.dist-info/RECORD
